aidungeonapi/__init__.py
aidungeonapi/aidadventure.py
aidungeonapi/aidclient.py
aidungeonapi/aidscenario.py
aidungeonapi/aobject.py
aidungeonapi-0.0.6.dist-info/LICENSE
aidungeonapi-0.0.6.dist-info/METADATA
aidungeonapi-0.0.6.dist-info/WHEEL
aidungeonapi-0.0.6.dist-info/top_level.txt
aidungeonapi-0.0.6.dist-info/RECORD
