Metadata-Version: 2.1
Name: aidungeonapi
Version: 0.0.6
Summary: AI Dungeon api for python
Home-page: https://github.com/1Macho/AIDungeonAPI
Author: 1Macho
Author-email: ozjuanpa@gmail.com
License: UNKNOWN
Platform: UNKNOWN
Classifier: Programming Language :: Python :: 3
Classifier: License :: OSI Approved :: MIT License
Classifier: Operating System :: OS Independent
Requires-Python: >=3.6
Requires-Dist: gql (>=v3.0.0a1)
